{"owner_type":"orgs","package_type":"container","owner_id":187275343,"owner":"pkgforge","repo":"bincache","package":"bincache%2Fdesync%2Fofficial%2Fsource%2Fdesync","date":"2025-04-05","size":"25.4 MB","versions":"1","tagged":"1","owner_rank":"3.9k","repo_rank":"3.6k","downloads":"2","downloads_month":"2","downloads_week":"2","downloads_day":"2","raw_size":25468073,"raw_versions":1,"raw_tagged":1,"raw_owner_rank":3990,"raw_repo_rank":3620,"raw_downloads":2,"raw_downloads_month":2,"raw_downloads_week":2,"raw_downloads_day":2,"version":[{"id":389004688,"name":"sha256:1edf081b865ef348392ba02843be361e66a2659f2307ed5abcf412f62aa8981e","date":"2025-04-05","newest":true,"latest":true,"size":"25.4 MB","downloads":"2","downloads_month":"2","downloads_week":"2","downloads_day":"2","raw_size":25468073,"raw_downloads":2,"raw_downloads_month":2,"raw_downloads_week":2,"raw_downloads_day":2,"tags":["HEAD-a180a01-250314T100117-x86_64-linux"]}]}
