{"owner_type":"orgs","package_type":"container","owner_id":187275343,"owner":"pkgforge","repo":"bincache","package":"bincache%2Fphp%2Fcrazywhalecc%2Fphp-common-fpm","date":"2025-04-16","size":"9.3 MB","versions":"4","tagged":"2","owner_rank":"3.4k","repo_rank":"3.1k","downloads":"393","downloads_month":"259","downloads_week":"63","downloads_day":"6","raw_size":9372532,"raw_versions":4,"raw_tagged":2,"raw_owner_rank":3435,"raw_repo_rank":3199,"raw_downloads":393,"raw_downloads_month":259,"raw_downloads_week":63,"raw_downloads_day":6,"version":[{"id":365690252,"name":"sha256:2e2f29e3c32c6959809951c475090f62c6b53344e9370afe91a89f07014eefc8","date":"2025-04-16","newest":false,"latest":false,"size":"-1","downloads":"0","downloads_month":"0","downloads_week":"0","downloads_day":"0","raw_size":-1,"raw_downloads":0,"raw_downloads_month":0,"raw_downloads_week":0,"raw_downloads_day":0,"tags":[]},{"id":365690261,"name":"sha256:8eecd89e930312b2eafbb54172f90644ca1508d3e47c7fed747f9fbb1872ce6a","date":"2025-04-16","newest":false,"latest":false,"size":"9.1 MB","downloads":"198","downloads_month":"131","downloads_week":"32","downloads_day":"3","raw_size":9195802,"raw_downloads":198,"raw_downloads_month":131,"raw_downloads_week":32,"raw_downloads_day":3,"tags":["8.4.4-x86_64-linux"]},{"id":365690823,"name":"sha256:c3afa206cb4ca3e6c9ca34637749fd8a9f84c719b0728841c5af2068345ad24f","date":"2025-04-16","newest":false,"latest":false,"size":"-1","downloads":"0","downloads_month":"0","downloads_week":"0","downloads_day":"0","raw_size":-1,"raw_downloads":0,"raw_downloads_month":0,"raw_downloads_week":0,"raw_downloads_day":0,"tags":[]},{"id":365690845,"name":"sha256:df3b00b38a4e8aa09f3202e2600e6e1510e78b840abd453e525978f6e94b9beb","date":"2025-04-16","newest":true,"latest":true,"size":"9.3 MB","downloads":"195","downloads_month":"128","downloads_week":"31","downloads_day":"3","raw_size":9372532,"raw_downloads":195,"raw_downloads_month":128,"raw_downloads_week":31,"raw_downloads_day":3,"tags":["8.4.4-aarch64-linux"]}]}
