{"owner_type":"orgs","package_type":"container","owner_id":187275343,"owner":"pkgforge","repo":"bincache","package":"bincache%2Fxz%2Fnixpkgs%2Flzma","date":"2025-02-24","size":"600 kB","versions":"1","tagged":"1","owner_rank":"2.6k","repo_rank":"2.4k","downloads":"119","downloads_month":"-1","downloads_week":"-1","downloads_day":"-1","raw_size":600030,"raw_versions":1,"raw_tagged":1,"raw_owner_rank":2602,"raw_repo_rank":2483,"raw_downloads":119,"raw_downloads_month":-1,"raw_downloads_week":-1,"raw_downloads_day":-1,"version":[{"id":355621570,"name":"sha256:8741fcdaf972468d4da26c9bc2d3d7bb78eedacecc55989dbdd7212fac70532b","date":"2025-02-24","newest":true,"latest":true,"size":"600 kB","downloads":"54","downloads_month":"54","downloads_week":"37","downloads_day":"4","raw_size":600030,"raw_downloads":54,"raw_downloads_month":54,"raw_downloads_week":37,"raw_downloads_day":4,"tags":["5.6.3-aarch64-linux"]}]}
