<?xml version="1.0" encoding="UTF-8"?><xml><owner_type>orgs</owner_type><package_type>container</package_type><owner_id>187275343</owner_id><owner>pkgforge</owner><repo>bincache</repo><package>bincache%2Fshadow%2Fofficial%2Fchpasswd</package><date>2025-04-13</date><size>4.3 MB</size><versions>4</versions><tagged>2</tagged><owner_rank>1.9k</owner_rank><repo_rank>1.7k</repo_rank><downloads>349</downloads><downloads_month>253</downloads_month><downloads_week>63</downloads_week><downloads_day>2</downloads_day><raw_size>4367649</raw_size><raw_versions>4</raw_versions><raw_tagged>2</raw_tagged><raw_owner_rank>1991</raw_owner_rank><raw_repo_rank>1772</raw_repo_rank><raw_downloads>349</raw_downloads><raw_downloads_month>253</raw_downloads_month><raw_downloads_week>63</raw_downloads_week><raw_downloads_day>2</raw_downloads_day><version><id>367026636</id><name>sha256:0b49651cd3b070f9e2478af23690435d9a9733c32593b78a689a16493a0c3235</name><date>2025-04-13</date><newest>false</newest><latest>false</latest><size>-1</size><downloads>0</downloads><downloads_month>0</downloads_month><downloads_week>0</downloads_week><downloads_day>0</downloads_day><raw_size>-1</raw_size><raw_downloads>0</raw_downloads><raw_downloads_month>0</raw_downloads_month><raw_downloads_week>0</raw_downloads_week><raw_downloads_day>0</raw_downloads_day></version><version><id>367026676</id><name>sha256:1440d67622e71fd694e00921c8c8b3c7b4a549b1aae333b3257241b26a872b17</name><date>2025-04-13</date><newest>false</newest><latest>false</latest><size>4.4 MB</size><downloads>170</downloads><downloads_month>125</downloads_month><downloads_week>31</downloads_week><downloads_day>1</downloads_day><raw_size>4464175</raw_size><raw_downloads>170</raw_downloads><raw_downloads_month>125</raw_downloads_month><raw_downloads_week>31</raw_downloads_week><raw_downloads_day>1</raw_downloads_day><tags>4.17.2-aarch64-linux</tags></version><version><id>367027336</id><name>sha256:9533199d38d2924a7b1835fdfccc79806cd7a1f5f92ec0a7c0dc9d26412a7f73</name><date>2025-04-13</date><newest>false</newest><latest>false</latest><size>-1</size><downloads>0</downloads><downloads_month>0</downloads_month><downloads_week>0</downloads_week><downloads_day>0</downloads_day><raw_size>-1</raw_size><raw_downloads>0</raw_downloads><raw_downloads_month>0</raw_downloads_month><raw_downloads_week>0</raw_downloads_week><raw_downloads_day>0</raw_downloads_day></version><version><id>367027399</id><name>sha256:ba95f176a518aaa7f95dad928c4cfbe7ec306667fea43bcc851eab9a0c575218</name><date>2025-04-13</date><newest>true</newest><latest>true</latest><size>4.3 MB</size><downloads>171</downloads><downloads_month>128</downloads_month><downloads_week>32</downloads_week><downloads_day>1</downloads_day><raw_size>4367649</raw_size><raw_downloads>171</raw_downloads><raw_downloads_month>128</raw_downloads_month><raw_downloads_week>32</raw_downloads_week><raw_downloads_day>1</raw_downloads_day><tags>4.17.2-x86_64-linux</tags></version></xml>
