{"owner_type":"orgs","package_type":"container","owner_id":187275343,"owner":"pkgforge","repo":"bincache","package":"bincache%2Fdateutils%2Fnixpkgs%2Fdatediff","date":"2025-01-08","size":"3.3 MB","versions":"3","tagged":"3","owner_rank":"209","repo_rank":"209","downloads":"77","downloads_month":"56","downloads_week":"55","downloads_day":"4","raw_size":3375606,"raw_versions":3,"raw_tagged":3,"raw_owner_rank":209,"raw_repo_rank":209,"raw_downloads":77,"raw_downloads_month":56,"raw_downloads_week":55,"raw_downloads_day":4,"version":[{"id":327146732,"name":"sha256:2b415c0295b14d07d25c24d42f02038002c82d6c77caab5a4d0d8058f676e548","date":"2025-01-08","newest":false,"latest":false,"size":"3.2 MB","downloads":"1","downloads_month":"1","downloads_week":"0","downloads_day":"0","raw_size":3231276,"raw_downloads":1,"raw_downloads_month":1,"raw_downloads_week":0,"raw_downloads_day":0,"tags":["0.4.11"]},{"id":330408729,"name":"sha256:d4ff4dca0b41cbe1c7e910772d87a9f99c7c857ba1f1037e80bd18d37b7a799a","date":"2025-01-08","newest":false,"latest":false,"size":"3.5 MB","downloads":"34","downloads_month":"34","downloads_week":"34","downloads_day":"4","raw_size":3543132,"raw_downloads":34,"raw_downloads_month":34,"raw_downloads_week":34,"raw_downloads_day":4,"tags":["0.4.11-aarch64-linux"]},{"id":330417816,"name":"sha256:4ef30f6e564f1c1500e399e95a6db726295508e5e147cfeb0d12c272bbd18626","date":"2025-01-08","newest":true,"latest":true,"size":"3.3 MB","downloads":"21","downloads_month":"21","downloads_week":"21","downloads_day":"0","raw_size":3375606,"raw_downloads":21,"raw_downloads_month":21,"raw_downloads_week":21,"raw_downloads_day":0,"tags":["0.4.11"]}]}
