{"owner_type":"orgs","package_type":"container","owner_id":187275343,"owner":"pkgforge","repo":"bincache","package":"bincache%2Fcertspotter%2Fcertspotter","date":"2025-04-14","size":"5.9 MB","versions":"31","tagged":"31","owner_rank":"4.4k","repo_rank":"4k","downloads":"0","downloads_month":"0","downloads_week":"0","downloads_day":"0","raw_size":5968262,"raw_versions":31,"raw_tagged":31,"raw_owner_rank":4418,"raw_repo_rank":4034,"raw_downloads":0,"raw_downloads_month":0,"raw_downloads_week":0,"raw_downloads_day":0,"version":[{"id":322464319,"name":"sha256:1f88fc2a23514e2b483414a9e2641b616588cc027a31283616743288a17d9028","date":"2025-04-14","newest":false,"latest":false,"size":"5.7 MB","downloads":"0","downloads_month":"0","downloads_week":"0","downloads_day":"0","raw_size":5716198,"raw_downloads":0,"raw_downloads_month":0,"raw_downloads_week":0,"raw_downloads_day":0,"tags":["241213T173721"]},{"id":322468065,"name":"sha256:f922142106a79559d3de41544e9f252530e8b222da76b6d696537b3249f588fe","date":"2025-04-14","newest":false,"latest":false,"size":"5.9 MB","downloads":"0","downloads_month":"0","downloads_week":"0","downloads_day":"0","raw_size":5965668,"raw_downloads":0,"raw_downloads_month":0,"raw_downloads_week":0,"raw_downloads_day":0,"tags":["241213T174147"]},{"id":322512551,"name":"sha256:9e0ffbca03fd7ccb838bdff98e358fe6c3af94374392cc8ce92cd318a9b5a1a7","date":"2025-04-14","newest":false,"latest":false,"size":"5.7 MB","downloads":"0","downloads_month":"0","downloads_week":"0","downloads_day":"0","raw_size":5716234,"raw_downloads":0,"raw_downloads_month":0,"raw_downloads_week":0,"raw_downloads_day":0,"tags":["241213T191933"]},{"id":322519914,"name":"sha256:1e53c9f1ccb678e0d946b4ba1004734e6fcb1c384bf55adb3fa1edbc8d99be54","date":"2025-04-14","newest":false,"latest":false,"size":"5.9 MB","downloads":"0","downloads_month":"0","downloads_week":"0","downloads_day":"0","raw_size":5965704,"raw_downloads":0,"raw_downloads_month":0,"raw_downloads_week":0,"raw_downloads_day":0,"tags":["241213T193039"]},{"id":322689936,"name":"sha256:03d13a05de53ac75878ea0933171e31548a1f2d5bdc50ca15d0fc9ef93f383f7","date":"2025-04-14","newest":false,"latest":false,"size":"5.7 MB","downloads":"0","downloads_month":"0","downloads_week":"0","downloads_day":"0","raw_size":5718858,"raw_downloads":0,"raw_downloads_month":0,"raw_downloads_week":0,"raw_downloads_day":0,"tags":["v0.18.0"]},{"id":322693681,"name":"sha256:2b8130ad78fd3597b8b214d3ef275c6316e7bc8d279a1386d4c22196107958bd","date":"2025-04-14","newest":false,"latest":false,"size":"5.7 MB","downloads":"0","downloads_month":"0","downloads_week":"0","downloads_day":"0","raw_size":5718843,"raw_downloads":0,"raw_downloads_month":0,"raw_downloads_week":0,"raw_downloads_day":0,"tags":["v0.18.0"]},{"id":322698263,"name":"sha256:b2033752d503c11d86c8094b438d1034abe46843d9303b46a62dbcc0ea02457f","date":"2025-04-14","newest":false,"latest":false,"size":"5.9 MB","downloads":"0","downloads_month":"0","downloads_week":"0","downloads_day":"0","raw_size":5968305,"raw_downloads":0,"raw_downloads_month":0,"raw_downloads_week":0,"raw_downloads_day":0,"tags":["v0.18.0"]},{"id":322751382,"name":"sha256:19b4f2b0f2605235de32f32e5410d05343142484d3e825e4b389ac01a485bb7e","date":"2025-04-14","newest":false,"latest":false,"size":"5.7 MB","downloads":"0","downloads_month":"0","downloads_week":"0","downloads_day":"0","raw_size":5718839,"raw_downloads":0,"raw_downloads_month":0,"raw_downloads_week":0,"raw_downloads_day":0,"tags":["v0.18.0"]},{"id":322755435,"name":"sha256:53eb4c14f018eba5b5efed01d24e2d86aef8846ebbb78638e7d76c3242223433","date":"2025-04-14","newest":false,"latest":false,"size":"5.9 MB","downloads":"0","downloads_month":"0","downloads_week":"0","downloads_day":"0","raw_size":5968301,"raw_downloads":0,"raw_downloads_month":0,"raw_downloads_week":0,"raw_downloads_day":0,"tags":["v0.18.0"]},{"id":322881937,"name":"sha256:3175273b78e45cbd3ec9bfa290a9324e52a4bb295be25b327f9b9a03fe6002e9","date":"2025-04-14","newest":false,"latest":false,"size":"5.7 MB","downloads":"0","downloads_month":"0","downloads_week":"0","downloads_day":"0","raw_size":5718839,"raw_downloads":0,"raw_downloads_month":0,"raw_downloads_week":0,"raw_downloads_day":0,"tags":["v0.18.0"]},{"id":322887386,"name":"sha256:492c88529554aa2b4b42f4fc14e6f87cec3a016c63dd909a1556d367d7ef2a26","date":"2025-04-14","newest":false,"latest":false,"size":"5.9 MB","downloads":"0","downloads_month":"0","downloads_week":"0","downloads_day":"0","raw_size":5968301,"raw_downloads":0,"raw_downloads_month":0,"raw_downloads_week":0,"raw_downloads_day":0,"tags":["v0.18.0"]},{"id":323907084,"name":"sha256:6dee119ca0c218440d73085a0238f04e3e1ae38f5a63ef5dcffbd5b4b9c4c1d9","date":"2025-04-14","newest":false,"latest":false,"size":"5.7 MB","downloads":"0","downloads_month":"0","downloads_week":"0","downloads_day":"0","raw_size":5718800,"raw_downloads":0,"raw_downloads_month":0,"raw_downloads_week":0,"raw_downloads_day":0,"tags":["v0.18.0"]},{"id":323913248,"name":"sha256:cb7d24ab82f5d6bcbb2ea0ff529d8c52915ad96742c00bbab48548ede32d0ef3","date":"2025-04-14","newest":false,"latest":false,"size":"5.9 MB","downloads":"0","downloads_month":"0","downloads_week":"0","downloads_day":"0","raw_size":5968262,"raw_downloads":0,"raw_downloads_month":0,"raw_downloads_week":0,"raw_downloads_day":0,"tags":["v0.18.0"]},{"id":325377703,"name":"sha256:4c21bbe327f10a2f7b9a956c72b20f2b77c6922758f27318e0ddfb46ced70767","date":"2025-04-14","newest":false,"latest":false,"size":"5.7 MB","downloads":"0","downloads_month":"0","downloads_week":"0","downloads_day":"0","raw_size":5718800,"raw_downloads":0,"raw_downloads_month":0,"raw_downloads_week":0,"raw_downloads_day":0,"tags":["v0.18.0"]},{"id":325383769,"name":"sha256:cf5e3f40a07a27f8d12368b697d0fd107b6440b0073bfef973325ec90b83d972","date":"2025-04-14","newest":false,"latest":false,"size":"5.9 MB","downloads":"0","downloads_month":"0","downloads_week":"0","downloads_day":"0","raw_size":5968262,"raw_downloads":0,"raw_downloads_month":0,"raw_downloads_week":0,"raw_downloads_day":0,"tags":["v0.18.0"]},{"id":326611939,"name":"sha256:542717f5e02c4e7d6c5d9947700a74158fcd032cd7664876575cf5ce3274b9c0","date":"2025-04-14","newest":false,"latest":false,"size":"5.7 MB","downloads":"0","downloads_month":"0","downloads_week":"0","downloads_day":"0","raw_size":5718800,"raw_downloads":0,"raw_downloads_month":0,"raw_downloads_week":0,"raw_downloads_day":0,"tags":["v0.18.0"]},{"id":326616146,"name":"sha256:e7ed6856db354b660b805893e7279597b5bb4396c19dbf072e9e98b2a34fa834","date":"2025-04-14","newest":false,"latest":false,"size":"5.9 MB","downloads":"0","downloads_month":"0","downloads_week":"0","downloads_day":"0","raw_size":5968262,"raw_downloads":0,"raw_downloads_month":0,"raw_downloads_week":0,"raw_downloads_day":0,"tags":["v0.18.0"]},{"id":327090523,"name":"sha256:065f2a81bd7894e566ed9b0cab7e33862828c4b826b45955c1c3b1e3954e1648","date":"2025-04-14","newest":false,"latest":false,"size":"5.7 MB","downloads":"0","downloads_month":"0","downloads_week":"0","downloads_day":"0","raw_size":5718800,"raw_downloads":0,"raw_downloads_month":0,"raw_downloads_week":0,"raw_downloads_day":0,"tags":["v0.18.0"]},{"id":327096334,"name":"sha256:a27974398a05b1273ae18f339bda8f8328a769cd1cf3a6fd3704177bc8196f74","date":"2025-04-14","newest":false,"latest":false,"size":"5.9 MB","downloads":"0","downloads_month":"0","downloads_week":"0","downloads_day":"0","raw_size":5968262,"raw_downloads":0,"raw_downloads_month":0,"raw_downloads_week":0,"raw_downloads_day":0,"tags":["v0.18.0"]},{"id":327883325,"name":"sha256:90686906b1059184f6d1ce8b3098911530607435bbf151a324622a46ed347321","date":"2025-04-14","newest":false,"latest":false,"size":"5.7 MB","downloads":"0","downloads_month":"0","downloads_week":"0","downloads_day":"0","raw_size":5718800,"raw_downloads":0,"raw_downloads_month":0,"raw_downloads_week":0,"raw_downloads_day":0,"tags":["v0.18.0"]},{"id":327888152,"name":"sha256:62bf7754eb6b67d79c17106cc43c11860be7e25a415133de750874215b89de83","date":"2025-04-14","newest":false,"latest":false,"size":"5.9 MB","downloads":"0","downloads_month":"0","downloads_week":"0","downloads_day":"0","raw_size":5968262,"raw_downloads":0,"raw_downloads_month":0,"raw_downloads_week":0,"raw_downloads_day":0,"tags":["v0.18.0"]},{"id":328430733,"name":"sha256:4881f3c6a13351021c69ab6e705dc69ece8d6c7b6c446f75e6268def15e5f04a","date":"2025-04-14","newest":false,"latest":false,"size":"5.7 MB","downloads":"0","downloads_month":"0","downloads_week":"0","downloads_day":"0","raw_size":5718800,"raw_downloads":0,"raw_downloads_month":0,"raw_downloads_week":0,"raw_downloads_day":0,"tags":["v0.18.0"]},{"id":328435739,"name":"sha256:cb9a6f23ca3ea573dd988821a230125578e53868e66eec402693b3699bd47c93","date":"2025-04-14","newest":false,"latest":false,"size":"5.9 MB","downloads":"0","downloads_month":"0","downloads_week":"0","downloads_day":"0","raw_size":5968262,"raw_downloads":0,"raw_downloads_month":0,"raw_downloads_week":0,"raw_downloads_day":0,"tags":["v0.18.0"]},{"id":328952382,"name":"sha256:240d2f09ac102a2e59d43705a71d24a6033e53d273397ae9d5478af4e7adaed7","date":"2025-04-14","newest":false,"latest":false,"size":"5.7 MB","downloads":"0","downloads_month":"0","downloads_week":"0","downloads_day":"0","raw_size":5718800,"raw_downloads":0,"raw_downloads_month":0,"raw_downloads_week":0,"raw_downloads_day":0,"tags":["v0.18.0"]},{"id":328957350,"name":"sha256:8205a3b3b873cbc31da9f49265eb47c12aebe6e1a34c6abe0f9e9ce154c51a4f","date":"2025-04-14","newest":false,"latest":false,"size":"5.9 MB","downloads":"0","downloads_month":"0","downloads_week":"0","downloads_day":"0","raw_size":5968262,"raw_downloads":0,"raw_downloads_month":0,"raw_downloads_week":0,"raw_downloads_day":0,"tags":["v0.18.0"]},{"id":329556723,"name":"sha256:a037ae1d0d937746b7b2801e7012b4f5669ed12f050288287a460efd08ef98f0","date":"2025-04-14","newest":false,"latest":false,"size":"5.7 MB","downloads":"0","downloads_month":"0","downloads_week":"0","downloads_day":"0","raw_size":5718800,"raw_downloads":0,"raw_downloads_month":0,"raw_downloads_week":0,"raw_downloads_day":0,"tags":["v0.18.0"]},{"id":329561739,"name":"sha256:9e6744c2a11bb6ad8e818c50717cbd5a65bc9d2e557678fc1840b2bd38bfa0cb","date":"2025-04-14","newest":false,"latest":false,"size":"5.9 MB","downloads":"0","downloads_month":"0","downloads_week":"0","downloads_day":"0","raw_size":5968262,"raw_downloads":0,"raw_downloads_month":0,"raw_downloads_week":0,"raw_downloads_day":0,"tags":["v0.18.0"]},{"id":329872192,"name":"sha256:c3d4b2a9baed601fa2164886293529ab0404d1ace5f59081342b2bb885d9cb27","date":"2025-04-14","newest":false,"latest":false,"size":"5.7 MB","downloads":"0","downloads_month":"0","downloads_week":"0","downloads_day":"0","raw_size":5718800,"raw_downloads":0,"raw_downloads_month":0,"raw_downloads_week":0,"raw_downloads_day":0,"tags":["v0.18.0"]},{"id":329877267,"name":"sha256:1754e0e7f7790bca0135336f5fb3ae9b71f02c64c47b2e4a83453cbf6e83dfae","date":"2025-04-14","newest":false,"latest":false,"size":"5.9 MB","downloads":"0","downloads_month":"0","downloads_week":"0","downloads_day":"0","raw_size":5968262,"raw_downloads":0,"raw_downloads_month":0,"raw_downloads_week":0,"raw_downloads_day":0,"tags":["v0.18.0"]},{"id":330566483,"name":"sha256:deddba8afd246a6b814425727eeb7f37c2aded79ccdce3a360353f181bd47c82","date":"2025-04-14","newest":false,"latest":false,"size":"5.7 MB","downloads":"0","downloads_month":"0","downloads_week":"0","downloads_day":"0","raw_size":5718800,"raw_downloads":0,"raw_downloads_month":0,"raw_downloads_week":0,"raw_downloads_day":0,"tags":["aarch64"]},{"id":330571803,"name":"sha256:02a65f7425e536b0ba02fa7446fdb4622fd2ffec8bb298127b108b639069cc68","date":"2025-04-14","newest":true,"latest":true,"size":"5.9 MB","downloads":"0","downloads_month":"0","downloads_week":"0","downloads_day":"0","raw_size":5968262,"raw_downloads":0,"raw_downloads_month":0,"raw_downloads_week":0,"raw_downloads_day":0,"tags":["v0.18.0","x86_64"]}]}
