{"owner_type":"orgs","package_type":"container","owner_id":187275343,"owner":"pkgforge","repo":"bincache","package":"bincache%2Fcoreutils_uutils%2Fstandalone%2Fmore","date":"2025-03-14","size":"7 MB","versions":"3","tagged":"3","owner_rank":"131","repo_rank":"127","downloads":"1.5k","downloads_month":"18","downloads_week":"18","downloads_day":"6","raw_size":7039685,"raw_versions":3,"raw_tagged":3,"raw_owner_rank":131,"raw_repo_rank":127,"raw_downloads":1561,"raw_downloads_month":18,"raw_downloads_week":18,"raw_downloads_day":6,"version":[{"id":368294146,"name":"sha256:cc213f877530fee498c264f6600eb3417382e6bc68eb7a151a776b9190af7e30","date":"2025-03-14","newest":false,"latest":false,"size":"7 MB","downloads":"13","downloads_month":"13","downloads_week":"13","downloads_day":"5","raw_size":7067025,"raw_downloads":13,"raw_downloads_month":13,"raw_downloads_week":13,"raw_downloads_day":5,"tags":["HEAD-38bbfce-250305T144205-aarch64-linux"]},{"id":370051515,"name":"sha256:bc7e5cd659026ff4d1f3c350a53c71a1be8455b349e5f9e197b20796ef917c24","date":"2025-03-14","newest":false,"latest":false,"size":"7.3 MB","downloads":"5","downloads_month":"5","downloads_week":"5","downloads_day":"3","raw_size":7384580,"raw_downloads":5,"raw_downloads_month":5,"raw_downloads_week":5,"raw_downloads_day":3,"tags":["HEAD-1acfa6c-250307T181433-x86_64-linux"]},{"id":372265187,"name":"sha256:a8c2fa274181dbcdd0a9a38b0513f0941e400480d0a7ba35fdde33e8286370eb","date":"2025-03-14","newest":true,"latest":true,"size":"7 MB","downloads":"18","downloads_month":"18","downloads_week":"18","downloads_day":"6","raw_size":7039685,"raw_downloads":18,"raw_downloads_month":18,"raw_downloads_week":18,"raw_downloads_day":6,"tags":["HEAD-9bbe579-250311T155449-aarch64-linux"]}]}
