{"owner_type":"orgs","package_type":"container","owner_id":187275343,"owner":"pkgforge","repo":"bincache","package":"bincache%2Flibarchive%2Fbsdcat","date":"2025-02-01","size":"438.6 kB","versions":"1","tagged":"1","owner_rank":"2.9k","repo_rank":"2.8k","downloads":"0","downloads_month":"0","downloads_week":"0","downloads_day":"0","raw_size":438665,"raw_versions":1,"raw_tagged":1,"raw_owner_rank":2979,"raw_repo_rank":2877,"raw_downloads":0,"raw_downloads_month":0,"raw_downloads_week":0,"raw_downloads_day":0,"version":[{"id":330570456,"name":"sha256:646eed813e396de989115484e81b200c15cd7c4b3fbad739d8c2cdce17c22168","date":"2025-02-01","newest":true,"latest":true,"size":"438.6 kB","downloads":"0","downloads_month":"0","downloads_week":"0","downloads_day":"0","raw_size":438665,"raw_downloads":0,"raw_downloads_month":0,"raw_downloads_week":0,"raw_downloads_day":0,"tags":["19700101053001","x86_64"]}]}
