{"owner_type":"orgs","package_type":"container","owner_id":187275343,"owner":"pkgforge","repo":"bincache","package":"bincache%2Fcoreutils%2Fvlang%2Fcp","date":"2025-01-29","size":"2.5 MB","versions":"2","tagged":"2","owner_rank":"1.4k","repo_rank":"1.4k","downloads":"174","downloads_month":"21","downloads_week":"21","downloads_day":"4","raw_size":2541036,"raw_versions":2,"raw_tagged":2,"raw_owner_rank":1499,"raw_repo_rank":1421,"raw_downloads":174,"raw_downloads_month":21,"raw_downloads_week":21,"raw_downloads_day":4,"version":[{"id":343362803,"name":"sha256:b3f163d89b7f418a739ed1942bd18da3107179baa67bf25de14b1cdc1edac751","date":"2025-01-29","newest":false,"latest":false,"size":"2.5 MB","downloads":"33","downloads_month":"33","downloads_week":"33","downloads_day":"16","raw_size":2532533,"raw_downloads":33,"raw_downloads_month":33,"raw_downloads_week":33,"raw_downloads_day":16,"tags":["HEAD-b082754-241226T203319-x86_64-linux"]},{"id":343834923,"name":"sha256:47b1dc857984d30becabc42613be2198c9e16cda384a7571cec76b47da23d575","date":"2025-01-29","newest":true,"latest":true,"size":"2.5 MB","downloads":"21","downloads_month":"21","downloads_week":"21","downloads_day":"4","raw_size":2541036,"raw_downloads":21,"raw_downloads_month":21,"raw_downloads_week":21,"raw_downloads_day":4,"tags":["HEAD-b082754-241226T203319-aarch64-linux"]}]}
