<?xml version="1.0" encoding="UTF-8"?><xml><owner_type>orgs</owner_type><package_type>container</package_type><owner_id>187275343</owner_id><owner>pkgforge</owner><repo>bincache</repo><package>bincache%2Fzgrab2%2Fzgrab2</package><date>2025-04-17</date><size>13.7 MB</size><versions>30</versions><tagged>30</tagged><owner_rank>4.9k</owner_rank><repo_rank>4.3k</repo_rank><downloads>0</downloads><downloads_month>0</downloads_month><downloads_week>0</downloads_week><downloads_day>0</downloads_day><raw_size>13736802</raw_size><raw_versions>30</raw_versions><raw_tagged>30</raw_tagged><raw_owner_rank>4954</raw_owner_rank><raw_repo_rank>4376</raw_repo_rank><raw_downloads>0</raw_downloads><raw_downloads_month>0</raw_downloads_month><raw_downloads_week>0</raw_downloads_week><raw_downloads_day>0</raw_downloads_day><version><id>322465742</id><name>sha256:dccb44b57ed131142982cc2809ec134baa20e620f8f1053995178c809b1a56d8</name><date>2025-04-17</date><newest>false</newest><latest>false</latest><size>13.2 MB</size><downloads>0</downloads><downloads_month>0</downloads_month><downloads_week>0</downloads_week><downloads_day>0</downloads_day><raw_size>13239163</raw_size><raw_downloads>0</raw_downloads><raw_downloads_month>0</raw_downloads_month><raw_downloads_week>0</raw_downloads_week><raw_downloads_day>0</raw_downloads_day><tags>241213T173904</tags></version><version><id>322469963</id><name>sha256:256b8245aa5976b2deb6af217b71d03e681f866f126828b828d9d4a21781028e</name><date>2025-04-17</date><newest>false</newest><latest>false</latest><size>13.7 MB</size><downloads>0</downloads><downloads_month>0</downloads_month><downloads_week>0</downloads_week><downloads_day>0</downloads_day><raw_size>13734425</raw_size><raw_downloads>0</raw_downloads><raw_downloads_month>0</raw_downloads_month><raw_downloads_week>0</raw_downloads_week><raw_downloads_day>0</raw_downloads_day><tags>241213T174338</tags></version><version><id>322514915</id><name>sha256:99a0ca6e2de67fdaab2ae942c585fc71fd59b1ebc9ce60bc411a50961d3e7864</name><date>2025-04-17</date><newest>false</newest><latest>false</latest><size>13.2 MB</size><downloads>0</downloads><downloads_month>0</downloads_month><downloads_week>0</downloads_week><downloads_day>0</downloads_day><raw_size>13239190</raw_size><raw_downloads>0</raw_downloads><raw_downloads_month>0</raw_downloads_month><raw_downloads_week>0</raw_downloads_week><raw_downloads_day>0</raw_downloads_day><tags>241213T192313</tags></version><version><id>322522667</id><name>sha256:10501037bff131293cbe3167eb7580292a1f2b373503620f026371d719f7d85c</name><date>2025-04-17</date><newest>false</newest><latest>false</latest><size>13.7 MB</size><downloads>0</downloads><downloads_month>0</downloads_month><downloads_week>0</downloads_week><downloads_day>0</downloads_day><raw_size>13734452</raw_size><raw_downloads>0</raw_downloads><raw_downloads_month>0</raw_downloads_month><raw_downloads_week>0</raw_downloads_week><raw_downloads_day>0</raw_downloads_day><tags>241213T193451</tags></version><version><id>322695130</id><name>sha256:2885b24ee7b9a1e23b4077e195bb5e74c2db6b30696a0801fb911fcd3c2d0650</name><date>2025-04-17</date><newest>false</newest><latest>false</latest><size>13.2 MB</size><downloads>0</downloads><downloads_month>0</downloads_month><downloads_week>0</downloads_week><downloads_day>0</downloads_day><raw_size>13241596</raw_size><raw_downloads>0</raw_downloads><raw_downloads_month>0</raw_downloads_month><raw_downloads_week>0</raw_downloads_week><raw_downloads_day>0</raw_downloads_day><tags>v0.1.8</tags></version><version><id>322699646</id><name>sha256:a5a30236f8e12bf8e7d83644f7e4e181b4ff9c7ed142f97e0eae388cce40e31a</name><date>2025-04-17</date><newest>false</newest><latest>false</latest><size>13.7 MB</size><downloads>0</downloads><downloads_month>0</downloads_month><downloads_week>0</downloads_week><downloads_day>0</downloads_day><raw_size>13736850</raw_size><raw_downloads>0</raw_downloads><raw_downloads_month>0</raw_downloads_month><raw_downloads_week>0</raw_downloads_week><raw_downloads_day>0</raw_downloads_day><tags>v0.1.8</tags></version><version><id>322752645</id><name>sha256:905d60e112b9761269b36ced07fb0cf00e885275f6303cbabd67f6d4dd5b20df</name><date>2025-04-17</date><newest>false</newest><latest>false</latest><size>13.2 MB</size><downloads>0</downloads><downloads_month>0</downloads_month><downloads_week>0</downloads_week><downloads_day>0</downloads_day><raw_size>13241592</raw_size><raw_downloads>0</raw_downloads><raw_downloads_month>0</raw_downloads_month><raw_downloads_week>0</raw_downloads_week><raw_downloads_day>0</raw_downloads_day><tags>v0.1.8</tags></version><version><id>322757049</id><name>sha256:70636f64913dcd5fbef65aa034c913444b7879b54d27a9c919469d983b0a937c</name><date>2025-04-17</date><newest>false</newest><latest>false</latest><size>13.7 MB</size><downloads>0</downloads><downloads_month>0</downloads_month><downloads_week>0</downloads_week><downloads_day>0</downloads_day><raw_size>13736846</raw_size><raw_downloads>0</raw_downloads><raw_downloads_month>0</raw_downloads_month><raw_downloads_week>0</raw_downloads_week><raw_downloads_day>0</raw_downloads_day><tags>v0.1.8</tags></version><version><id>322883537</id><name>sha256:8013b3ba4afc24d8439faa7f4f8314da22e9841da8b57ffead7c3c1c28394ae1</name><date>2025-04-17</date><newest>false</newest><latest>false</latest><size>13.2 MB</size><downloads>0</downloads><downloads_month>0</downloads_month><downloads_week>0</downloads_week><downloads_day>0</downloads_day><raw_size>13241592</raw_size><raw_downloads>0</raw_downloads><raw_downloads_month>0</raw_downloads_month><raw_downloads_week>0</raw_downloads_week><raw_downloads_day>0</raw_downloads_day><tags>v0.1.8</tags></version><version><id>322889075</id><name>sha256:73c80c6a4c238c833ebaf4d058ea07d96656ce6461aa6191414d6646b809512a</name><date>2025-04-17</date><newest>false</newest><latest>false</latest><size>13.7 MB</size><downloads>0</downloads><downloads_month>0</downloads_month><downloads_week>0</downloads_week><downloads_day>0</downloads_day><raw_size>13736846</raw_size><raw_downloads>0</raw_downloads><raw_downloads_month>0</raw_downloads_month><raw_downloads_week>0</raw_downloads_week><raw_downloads_day>0</raw_downloads_day><tags>v0.1.8</tags></version><version><id>323909106</id><name>sha256:5fc34d5cd86ebcd4b69c206e7e6cce936f70d7e1e2e84d6074d82fc702dddccb</name><date>2025-04-17</date><newest>false</newest><latest>false</latest><size>13.2 MB</size><downloads>0</downloads><downloads_month>0</downloads_month><downloads_week>0</downloads_week><downloads_day>0</downloads_day><raw_size>13241548</raw_size><raw_downloads>0</raw_downloads><raw_downloads_month>0</raw_downloads_month><raw_downloads_week>0</raw_downloads_week><raw_downloads_day>0</raw_downloads_day><tags>v0.1.8</tags></version><version><id>323916022</id><name>sha256:741c799b274476e9eb9d7dd328f7f309b7e917fcff94d7db9a03c3ee5cd212fb</name><date>2025-04-17</date><newest>false</newest><latest>false</latest><size>13.7 MB</size><downloads>0</downloads><downloads_month>0</downloads_month><downloads_week>0</downloads_week><downloads_day>0</downloads_day><raw_size>13736802</raw_size><raw_downloads>0</raw_downloads><raw_downloads_month>0</raw_downloads_month><raw_downloads_week>0</raw_downloads_week><raw_downloads_day>0</raw_downloads_day><tags>v0.1.8</tags></version><version><id>325379569</id><name>sha256:207818e9168dc72bfbaad7ca00fe06bcd0a7275620af405cca75fff36c5019e7</name><date>2025-04-17</date><newest>false</newest><latest>false</latest><size>13.2 MB</size><downloads>0</downloads><downloads_month>0</downloads_month><downloads_week>0</downloads_week><downloads_day>0</downloads_day><raw_size>13241548</raw_size><raw_downloads>0</raw_downloads><raw_downloads_month>0</raw_downloads_month><raw_downloads_week>0</raw_downloads_week><raw_downloads_day>0</raw_downloads_day><tags>v0.1.8</tags></version><version><id>325386280</id><name>sha256:e3856e1e3662094d0842e01285922aa43a84fc4571f71201fc680357a12713ec</name><date>2025-04-17</date><newest>false</newest><latest>false</latest><size>13.7 MB</size><downloads>0</downloads><downloads_month>0</downloads_month><downloads_week>0</downloads_week><downloads_day>0</downloads_day><raw_size>13736802</raw_size><raw_downloads>0</raw_downloads><raw_downloads_month>0</raw_downloads_month><raw_downloads_week>0</raw_downloads_week><raw_downloads_day>0</raw_downloads_day><tags>v0.1.8</tags></version><version><id>326613288</id><name>sha256:b2cf5b5139f70c7f816e17b96e3461bdc21f16eb4ead51ba2aeb239e5efe8e81</name><date>2025-04-17</date><newest>false</newest><latest>false</latest><size>13.2 MB</size><downloads>0</downloads><downloads_month>0</downloads_month><downloads_week>0</downloads_week><downloads_day>0</downloads_day><raw_size>13241548</raw_size><raw_downloads>0</raw_downloads><raw_downloads_month>0</raw_downloads_month><raw_downloads_week>0</raw_downloads_week><raw_downloads_day>0</raw_downloads_day><tags>v0.1.8</tags></version><version><id>326617897</id><name>sha256:a69cd4c3293406c955e6422bc0144b63a3d2df49945140c8a07ee437ff3a0d27</name><date>2025-04-17</date><newest>false</newest><latest>false</latest><size>13.7 MB</size><downloads>0</downloads><downloads_month>0</downloads_month><downloads_week>0</downloads_week><downloads_day>0</downloads_day><raw_size>13736802</raw_size><raw_downloads>0</raw_downloads><raw_downloads_month>0</raw_downloads_month><raw_downloads_week>0</raw_downloads_week><raw_downloads_day>0</raw_downloads_day><tags>v0.1.8</tags></version><version><id>327092376</id><name>sha256:d7ee9faa8470d14567cbcbf9d0b89d7c445c2997df24ab55875c032e1e260306</name><date>2025-04-17</date><newest>false</newest><latest>false</latest><size>13.2 MB</size><downloads>0</downloads><downloads_month>0</downloads_month><downloads_week>0</downloads_week><downloads_day>0</downloads_day><raw_size>13241548</raw_size><raw_downloads>0</raw_downloads><raw_downloads_month>0</raw_downloads_month><raw_downloads_week>0</raw_downloads_week><raw_downloads_day>0</raw_downloads_day><tags>v0.1.8</tags></version><version><id>327098447</id><name>sha256:750285b66c89194c66e7540d0fe8e51b949bd99969658d630fee28e09a4e5be8</name><date>2025-04-17</date><newest>false</newest><latest>false</latest><size>13.7 MB</size><downloads>0</downloads><downloads_month>0</downloads_month><downloads_week>0</downloads_week><downloads_day>0</downloads_day><raw_size>13736802</raw_size><raw_downloads>0</raw_downloads><raw_downloads_month>0</raw_downloads_month><raw_downloads_week>0</raw_downloads_week><raw_downloads_day>0</raw_downloads_day><tags>v0.1.8</tags></version><version><id>327884786</id><name>sha256:c37006183116899cadc1d1cfd2a4f8e6d390ae08f84da5dbf6a3fbfc2dbd8a57</name><date>2025-04-17</date><newest>false</newest><latest>false</latest><size>13.2 MB</size><downloads>0</downloads><downloads_month>0</downloads_month><downloads_week>0</downloads_week><downloads_day>0</downloads_day><raw_size>13241548</raw_size><raw_downloads>0</raw_downloads><raw_downloads_month>0</raw_downloads_month><raw_downloads_week>0</raw_downloads_week><raw_downloads_day>0</raw_downloads_day><tags>v0.1.8</tags></version><version><id>327890166</id><name>sha256:3ac27a7bc1366347f39728a041887c6d91bb3dc44f2d71a851661e4cc9b2eaa4</name><date>2025-04-17</date><newest>false</newest><latest>false</latest><size>13.7 MB</size><downloads>0</downloads><downloads_month>0</downloads_month><downloads_week>0</downloads_week><downloads_day>0</downloads_day><raw_size>13736802</raw_size><raw_downloads>0</raw_downloads><raw_downloads_month>0</raw_downloads_month><raw_downloads_week>0</raw_downloads_week><raw_downloads_day>0</raw_downloads_day><tags>v0.1.8</tags></version><version><id>328432347</id><name>sha256:e0d066e2f4f8dfb4c0a7e4978a6bb385295bbeccb27dd4c2781e269990b05e3c</name><date>2025-04-17</date><newest>false</newest><latest>false</latest><size>13.2 MB</size><downloads>0</downloads><downloads_month>0</downloads_month><downloads_week>0</downloads_week><downloads_day>0</downloads_day><raw_size>13241548</raw_size><raw_downloads>0</raw_downloads><raw_downloads_month>0</raw_downloads_month><raw_downloads_week>0</raw_downloads_week><raw_downloads_day>0</raw_downloads_day><tags>v0.1.8</tags></version><version><id>328437488</id><name>sha256:f5e37eb2f0110ac460b51ca7e2b337c86d47773b270a3419942821634efe3e51</name><date>2025-04-17</date><newest>false</newest><latest>false</latest><size>13.7 MB</size><downloads>0</downloads><downloads_month>0</downloads_month><downloads_week>0</downloads_week><downloads_day>0</downloads_day><raw_size>13736802</raw_size><raw_downloads>0</raw_downloads><raw_downloads_month>0</raw_downloads_month><raw_downloads_week>0</raw_downloads_week><raw_downloads_day>0</raw_downloads_day><tags>v0.1.8</tags></version><version><id>328954025</id><name>sha256:c5206753ad5d07c0fec64c1bb60038245dae85099597d522aefacd2770bee4da</name><date>2025-04-17</date><newest>false</newest><latest>false</latest><size>13.2 MB</size><downloads>0</downloads><downloads_month>0</downloads_month><downloads_week>0</downloads_week><downloads_day>0</downloads_day><raw_size>13241548</raw_size><raw_downloads>0</raw_downloads><raw_downloads_month>0</raw_downloads_month><raw_downloads_week>0</raw_downloads_week><raw_downloads_day>0</raw_downloads_day><tags>v0.1.8</tags></version><version><id>328959188</id><name>sha256:ce0d7b8caeead8d12870e48c9217f4ef1b14ec035823259e23c6b8770075586a</name><date>2025-04-17</date><newest>false</newest><latest>false</latest><size>13.7 MB</size><downloads>0</downloads><downloads_month>0</downloads_month><downloads_week>0</downloads_week><downloads_day>0</downloads_day><raw_size>13736802</raw_size><raw_downloads>0</raw_downloads><raw_downloads_month>0</raw_downloads_month><raw_downloads_week>0</raw_downloads_week><raw_downloads_day>0</raw_downloads_day><tags>v0.1.8</tags></version><version><id>329558226</id><name>sha256:0a305244150c97fd40070aeb65cfe3e158744f67002f11edc3a9b1c27a9a90b6</name><date>2025-04-17</date><newest>false</newest><latest>false</latest><size>13.2 MB</size><downloads>0</downloads><downloads_month>0</downloads_month><downloads_week>0</downloads_week><downloads_day>0</downloads_day><raw_size>13241548</raw_size><raw_downloads>0</raw_downloads><raw_downloads_month>0</raw_downloads_month><raw_downloads_week>0</raw_downloads_week><raw_downloads_day>0</raw_downloads_day><tags>v0.1.8</tags></version><version><id>329563516</id><name>sha256:493725ccc83c8e15112a37abb64676baf13e4ccd96e3e1478289ac54f77f8abc</name><date>2025-04-17</date><newest>false</newest><latest>false</latest><size>13.7 MB</size><downloads>0</downloads><downloads_month>0</downloads_month><downloads_week>0</downloads_week><downloads_day>0</downloads_day><raw_size>13736802</raw_size><raw_downloads>0</raw_downloads><raw_downloads_month>0</raw_downloads_month><raw_downloads_week>0</raw_downloads_week><raw_downloads_day>0</raw_downloads_day><tags>v0.1.8</tags></version><version><id>329873646</id><name>sha256:7c66bed8e56618d75f1f17218e6e3f7c2034ecb543ab256c20e2006276bbcdac</name><date>2025-04-17</date><newest>false</newest><latest>false</latest><size>13.2 MB</size><downloads>0</downloads><downloads_month>0</downloads_month><downloads_week>0</downloads_week><downloads_day>0</downloads_day><raw_size>13241548</raw_size><raw_downloads>0</raw_downloads><raw_downloads_month>0</raw_downloads_month><raw_downloads_week>0</raw_downloads_week><raw_downloads_day>0</raw_downloads_day><tags>v0.1.8</tags></version><version><id>329878933</id><name>sha256:262ec820a860df9fa6ac28cfb7001b2099f8aaecb72d9aa62da5ae0b6d8aa34f</name><date>2025-04-17</date><newest>false</newest><latest>false</latest><size>13.7 MB</size><downloads>0</downloads><downloads_month>0</downloads_month><downloads_week>0</downloads_week><downloads_day>0</downloads_day><raw_size>13736802</raw_size><raw_downloads>0</raw_downloads><raw_downloads_month>0</raw_downloads_month><raw_downloads_week>0</raw_downloads_week><raw_downloads_day>0</raw_downloads_day><tags>v0.1.8</tags></version><version><id>330567951</id><name>sha256:d40fa568d358aa4e4147d03b53be62cda8dab0e3e8d26124c6888ca53bd19e36</name><date>2025-04-17</date><newest>false</newest><latest>false</latest><size>13.2 MB</size><downloads>0</downloads><downloads_month>0</downloads_month><downloads_week>0</downloads_week><downloads_day>0</downloads_day><raw_size>13241548</raw_size><raw_downloads>0</raw_downloads><raw_downloads_month>0</raw_downloads_month><raw_downloads_week>0</raw_downloads_week><raw_downloads_day>0</raw_downloads_day><tags>aarch64</tags></version><version><id>330573442</id><name>sha256:ea41c33db3e28c0df8af0ab2a80317a3b6738e3e8a8a49898d807ea2a989651a</name><date>2025-04-17</date><newest>true</newest><latest>true</latest><size>13.7 MB</size><downloads>0</downloads><downloads_month>0</downloads_month><downloads_week>0</downloads_week><downloads_day>0</downloads_day><raw_size>13736802</raw_size><raw_downloads>0</raw_downloads><raw_downloads_month>0</raw_downloads_month><raw_downloads_week>0</raw_downloads_week><raw_downloads_day>0</raw_downloads_day><tags>v0.1.8</tags><tags>x86_64</tags></version></xml>
