{"owner_type":"orgs","package_type":"container","owner_id":187275343,"owner":"pkgforge","repo":"bincache","package":"bincache%2Fslim%2Fofficial%2Fdocker-slim-sensor","date":"2025-03-28","size":"11.6 MB","versions":"1","tagged":"1","owner_rank":"3.6k","repo_rank":"3.4k","downloads":"186","downloads_month":"93","downloads_week":"25","downloads_day":"1","raw_size":11646489,"raw_versions":1,"raw_tagged":1,"raw_owner_rank":3689,"raw_repo_rank":3427,"raw_downloads":186,"raw_downloads_month":93,"raw_downloads_week":25,"raw_downloads_day":1,"version":[{"id":369678343,"name":"sha256:b974f8599f8f5e65445f6922703f9dd6a73fbefb77c57b7e430eb9007ef9c6d7","date":"2025-03-28","newest":true,"latest":true,"size":"11.6 MB","downloads":"93","downloads_month":"93","downloads_week":"25","downloads_day":"1","raw_size":11646489,"raw_downloads":93,"raw_downloads_month":93,"raw_downloads_week":25,"raw_downloads_day":1,"tags":["HEAD-456a8b7-250130T101109-aarch64-linux"]}]}
