<?xml version="1.0" encoding="UTF-8"?><xml><owner_type>orgs</owner_type><package_type>container</package_type><owner_id>187275343</owner_id><owner>pkgforge</owner><repo>bincache</repo><package>bincache%2Fbusybox%2Fhdparm</package><date>2025-04-10</date><size>73.5 kB</size><versions>32</versions><tagged>32</tagged><owner_rank>1.3k</owner_rank><repo_rank>1k</repo_rank><downloads>0</downloads><downloads_month>0</downloads_month><downloads_week>0</downloads_week><downloads_day>0</downloads_day><raw_size>73533</raw_size><raw_versions>32</raw_versions><raw_tagged>32</raw_tagged><raw_owner_rank>1385</raw_owner_rank><raw_repo_rank>1027</raw_repo_rank><raw_downloads>0</raw_downloads><raw_downloads_month>0</raw_downloads_month><raw_downloads_week>0</raw_downloads_week><raw_downloads_day>0</raw_downloads_day><version><id>322459898</id><name>sha256:9d900e7b4602ca0b868fc56cb83c616238697f6f93d67507b5fb17136b448370</name><date>2025-04-10</date><newest>false</newest><latest>false</latest><size>133.6 kB</size><downloads>0</downloads><downloads_month>0</downloads_month><downloads_week>0</downloads_week><downloads_day>0</downloads_day><raw_size>133636</raw_size><raw_downloads>0</raw_downloads><raw_downloads_month>0</raw_downloads_month><raw_downloads_week>0</raw_downloads_week><raw_downloads_day>0</raw_downloads_day><tags>241213T173116</tags></version><version><id>322462143</id><name>sha256:9a8e79b65cac0ef1a3fa6411eb380ed42098d9b5e429ddfaf27e1df6f1cdda5b</name><date>2025-04-10</date><newest>false</newest><latest>false</latest><size>133.6 kB</size><downloads>0</downloads><downloads_month>0</downloads_month><downloads_week>0</downloads_week><downloads_day>0</downloads_day><raw_size>133636</raw_size><raw_downloads>0</raw_downloads><raw_downloads_month>0</raw_downloads_month><raw_downloads_week>0</raw_downloads_week><raw_downloads_day>0</raw_downloads_day><tags>241213T173502</tags></version><version><id>322505538</id><name>sha256:99b72dd96f8eee86039a96dae425b65f49be9ca7f19f74adce89142330be9645</name><date>2025-04-10</date><newest>false</newest><latest>false</latest><size>133.6 kB</size><downloads>0</downloads><downloads_month>0</downloads_month><downloads_week>0</downloads_week><downloads_day>0</downloads_day><raw_size>133636</raw_size><raw_downloads>0</raw_downloads><raw_downloads_month>0</raw_downloads_month><raw_downloads_week>0</raw_downloads_week><raw_downloads_day>0</raw_downloads_day><tags>241213T190851</tags></version><version><id>322508222</id><name>sha256:0dbfd8d402ab2fa35536c9a924963debb55fd12cab344ee28177b1c00dc89355</name><date>2025-04-10</date><newest>false</newest><latest>false</latest><size>133.7 kB</size><downloads>0</downloads><downloads_month>0</downloads_month><downloads_week>0</downloads_week><downloads_day>0</downloads_day><raw_size>133712</raw_size><raw_downloads>0</raw_downloads><raw_downloads_month>0</raw_downloads_month><raw_downloads_week>0</raw_downloads_week><raw_downloads_day>0</raw_downloads_day><tags>241213T191256</tags></version><version><id>322515374</id><name>sha256:021743aad43fa9af74dc1cb9756d1765fb0121289059dce758ffc608d4f8f059</name><date>2025-04-10</date><newest>false</newest><latest>false</latest><size>68.2 kB</size><downloads>0</downloads><downloads_month>0</downloads_month><downloads_week>0</downloads_week><downloads_day>0</downloads_day><raw_size>68277</raw_size><raw_downloads>0</raw_downloads><raw_downloads_month>0</raw_downloads_month><raw_downloads_week>0</raw_downloads_week><raw_downloads_day>0</raw_downloads_day><tags>241213T192354</tags></version><version><id>322687548</id><name>sha256:12883254b7e219e3df9a31c743b5e326d88a6a5e99474fb3f6bdf29d6d6e1ca9</name><date>2025-04-10</date><newest>false</newest><latest>false</latest><size>139 kB</size><downloads>0</downloads><downloads_month>0</downloads_month><downloads_week>0</downloads_week><downloads_day>0</downloads_day><raw_size>139024</raw_size><raw_downloads>0</raw_downloads><raw_downloads_month>0</raw_downloads_month><raw_downloads_week>0</raw_downloads_week><raw_downloads_day>0</raw_downloads_day><tags>latest</tags></version><version><id>322691001</id><name>sha256:d2467b702842c48330fddee0d8a544ba76a135afda034be7ccaba078cee87c3e</name><date>2025-04-10</date><newest>false</newest><latest>false</latest><size>139 kB</size><downloads>0</downloads><downloads_month>0</downloads_month><downloads_week>0</downloads_week><downloads_day>0</downloads_day><raw_size>139009</raw_size><raw_downloads>0</raw_downloads><raw_downloads_month>0</raw_downloads_month><raw_downloads_week>0</raw_downloads_week><raw_downloads_day>0</raw_downloads_day><tags>latest</tags></version><version><id>322695466</id><name>sha256:46eb0fd4b021fc6fd4420bdf9f7aa6ccef5ac999f7b4d0b39153ca8bf3f939f9</name><date>2025-04-10</date><newest>false</newest><latest>false</latest><size>73.5 kB</size><downloads>0</downloads><downloads_month>0</downloads_month><downloads_week>0</downloads_week><downloads_day>0</downloads_day><raw_size>73565</raw_size><raw_downloads>0</raw_downloads><raw_downloads_month>0</raw_downloads_month><raw_downloads_week>0</raw_downloads_week><raw_downloads_day>0</raw_downloads_day><tags>latest</tags></version><version><id>322749049</id><name>sha256:46c0d689e8e587e552278580683428ed911d17a351477dfabad8dad784d3be74</name><date>2025-04-10</date><newest>false</newest><latest>false</latest><size>139 kB</size><downloads>0</downloads><downloads_month>0</downloads_month><downloads_week>0</downloads_week><downloads_day>0</downloads_day><raw_size>139021</raw_size><raw_downloads>0</raw_downloads><raw_downloads_month>0</raw_downloads_month><raw_downloads_week>0</raw_downloads_week><raw_downloads_day>0</raw_downloads_day><tags>20241210044406</tags></version><version><id>322752885</id><name>sha256:8b43fb5930a1f07f6b7d40732902c82398f42ef92832ccef397e5ecb4537c8ea</name><date>2025-04-10</date><newest>false</newest><latest>false</latest><size>73.5 kB</size><downloads>0</downloads><downloads_month>0</downloads_month><downloads_week>0</downloads_week><downloads_day>0</downloads_day><raw_size>73577</raw_size><raw_downloads>0</raw_downloads><raw_downloads_month>0</raw_downloads_month><raw_downloads_week>0</raw_downloads_week><raw_downloads_day>0</raw_downloads_day><tags>20241210031140</tags></version><version><id>322878856</id><name>sha256:2f418f1164caadf452914b7140cf90881ce196f80406495f110cde11a263b210</name><date>2025-04-10</date><newest>false</newest><latest>false</latest><size>139 kB</size><downloads>0</downloads><downloads_month>0</downloads_month><downloads_week>0</downloads_week><downloads_day>0</downloads_day><raw_size>139021</raw_size><raw_downloads>0</raw_downloads><raw_downloads_month>0</raw_downloads_month><raw_downloads_week>0</raw_downloads_week><raw_downloads_day>0</raw_downloads_day><tags>20241210044406</tags></version><version><id>322883859</id><name>sha256:3b32a2f62bc17830f31fab277e4431f0a2ae696e40272164130918064b2b7839</name><date>2025-04-10</date><newest>false</newest><latest>false</latest><size>73.5 kB</size><downloads>0</downloads><downloads_month>0</downloads_month><downloads_week>0</downloads_week><downloads_day>0</downloads_day><raw_size>73577</raw_size><raw_downloads>0</raw_downloads><raw_downloads_month>0</raw_downloads_month><raw_downloads_week>0</raw_downloads_week><raw_downloads_day>0</raw_downloads_day><tags>20241210031140</tags></version><version><id>323903640</id><name>sha256:8cb6b05fb24c96a517d6c374cc02f7b3c115c09695755d9eb683f6948fb6f151</name><date>2025-04-10</date><newest>false</newest><latest>false</latest><size>138.9 kB</size><downloads>0</downloads><downloads_month>0</downloads_month><downloads_week>0</downloads_week><downloads_day>0</downloads_day><raw_size>138977</raw_size><raw_downloads>0</raw_downloads><raw_downloads_month>0</raw_downloads_month><raw_downloads_week>0</raw_downloads_week><raw_downloads_day>0</raw_downloads_day><tags>20241210044406</tags></version><version><id>323909519</id><name>sha256:17dd610fe49bf847e159702832aeb58411426088e09311dfb85dde8be61a4871</name><date>2025-04-10</date><newest>false</newest><latest>false</latest><size>73.5 kB</size><downloads>0</downloads><downloads_month>0</downloads_month><downloads_week>0</downloads_week><downloads_day>0</downloads_day><raw_size>73533</raw_size><raw_downloads>0</raw_downloads><raw_downloads_month>0</raw_downloads_month><raw_downloads_week>0</raw_downloads_week><raw_downloads_day>0</raw_downloads_day><tags>20241210031140</tags></version><version><id>325374429</id><name>sha256:10ece7b0f39efef3ca4d2b8852021a82b6fe439a673990b42035c80b0db2b2b7</name><date>2025-04-10</date><newest>false</newest><latest>false</latest><size>138.9 kB</size><downloads>0</downloads><downloads_month>0</downloads_month><downloads_week>0</downloads_week><downloads_day>0</downloads_day><raw_size>138977</raw_size><raw_downloads>0</raw_downloads><raw_downloads_month>0</raw_downloads_month><raw_downloads_week>0</raw_downloads_week><raw_downloads_day>0</raw_downloads_day><tags>20241210044406</tags></version><version><id>325379876</id><name>sha256:643ad365227c5597b396e7c8103986e4ef621508e4b44543ef7cb621cab60e97</name><date>2025-04-10</date><newest>false</newest><latest>false</latest><size>73.5 kB</size><downloads>0</downloads><downloads_month>0</downloads_month><downloads_week>0</downloads_week><downloads_day>0</downloads_day><raw_size>73533</raw_size><raw_downloads>0</raw_downloads><raw_downloads_month>0</raw_downloads_month><raw_downloads_week>0</raw_downloads_week><raw_downloads_day>0</raw_downloads_day><tags>20241210031140</tags></version><version><id>326608982</id><name>sha256:fd2c3f011fec4dfb5e5f7c621b882a9f5f7c0a5efcbde8645581411604de7172</name><date>2025-04-10</date><newest>false</newest><latest>false</latest><size>138.9 kB</size><downloads>0</downloads><downloads_month>0</downloads_month><downloads_week>0</downloads_week><downloads_day>0</downloads_day><raw_size>138977</raw_size><raw_downloads>0</raw_downloads><raw_downloads_month>0</raw_downloads_month><raw_downloads_week>0</raw_downloads_week><raw_downloads_day>0</raw_downloads_day><tags>20241210044406</tags></version><version><id>326613541</id><name>sha256:5e6162d281fa879f78fbda17351bf99d35758efc86461ce730f25cc50a2f7e4f</name><date>2025-04-10</date><newest>false</newest><latest>false</latest><size>73.5 kB</size><downloads>0</downloads><downloads_month>0</downloads_month><downloads_week>0</downloads_week><downloads_day>0</downloads_day><raw_size>73533</raw_size><raw_downloads>0</raw_downloads><raw_downloads_month>0</raw_downloads_month><raw_downloads_week>0</raw_downloads_week><raw_downloads_day>0</raw_downloads_day><tags>20241210031140</tags></version><version><id>327087266</id><name>sha256:b95c9154cb6b820395588928e3a7db6f237a3b7a5b1838f15bf624a935c8759a</name><date>2025-04-10</date><newest>false</newest><latest>false</latest><size>138.9 kB</size><downloads>0</downloads><downloads_month>0</downloads_month><downloads_week>0</downloads_week><downloads_day>0</downloads_day><raw_size>138977</raw_size><raw_downloads>0</raw_downloads><raw_downloads_month>0</raw_downloads_month><raw_downloads_week>0</raw_downloads_week><raw_downloads_day>0</raw_downloads_day><tags>20241210044406</tags></version><version><id>327092853</id><name>sha256:0b8d7f57b2a2a887500501cefc82a7f9beff7c99ee1bbcbd71484d679bbfe9db</name><date>2025-04-10</date><newest>false</newest><latest>false</latest><size>73.5 kB</size><downloads>0</downloads><downloads_month>0</downloads_month><downloads_week>0</downloads_week><downloads_day>0</downloads_day><raw_size>73533</raw_size><raw_downloads>0</raw_downloads><raw_downloads_month>0</raw_downloads_month><raw_downloads_week>0</raw_downloads_week><raw_downloads_day>0</raw_downloads_day><tags>20241210031140</tags></version><version><id>327880393</id><name>sha256:abfdabe2ac47c8498a37871da2252ea89d9934f7c72411bf6df859d535f25c7d</name><date>2025-04-10</date><newest>false</newest><latest>false</latest><size>138.9 kB</size><downloads>0</downloads><downloads_month>0</downloads_month><downloads_week>0</downloads_week><downloads_day>0</downloads_day><raw_size>138977</raw_size><raw_downloads>0</raw_downloads><raw_downloads_month>0</raw_downloads_month><raw_downloads_week>0</raw_downloads_week><raw_downloads_day>0</raw_downloads_day><tags>20241210044406</tags></version><version><id>327885113</id><name>sha256:05921abe2d554da0bfde60c6f5d4a7f8c291f3409170022067a0492e6a693a22</name><date>2025-04-10</date><newest>false</newest><latest>false</latest><size>73.5 kB</size><downloads>0</downloads><downloads_month>0</downloads_month><downloads_week>0</downloads_week><downloads_day>0</downloads_day><raw_size>73533</raw_size><raw_downloads>0</raw_downloads><raw_downloads_month>0</raw_downloads_month><raw_downloads_week>0</raw_downloads_week><raw_downloads_day>0</raw_downloads_day><tags>20241210031140</tags></version><version><id>328427839</id><name>sha256:fab22a04926760b887c945d374c40ffa540fa5c55ec4a938c3406cb28281b2a5</name><date>2025-04-10</date><newest>false</newest><latest>false</latest><size>138.9 kB</size><downloads>0</downloads><downloads_month>0</downloads_month><downloads_week>0</downloads_week><downloads_day>0</downloads_day><raw_size>138977</raw_size><raw_downloads>0</raw_downloads><raw_downloads_month>0</raw_downloads_month><raw_downloads_week>0</raw_downloads_week><raw_downloads_day>0</raw_downloads_day><tags>20241210044406</tags></version><version><id>328432621</id><name>sha256:794fd5a4dcaf1e784962f36c8b5436c434323028f1c31050a4249de39880528f</name><date>2025-04-10</date><newest>false</newest><latest>false</latest><size>73.5 kB</size><downloads>0</downloads><downloads_month>0</downloads_month><downloads_week>0</downloads_week><downloads_day>0</downloads_day><raw_size>73533</raw_size><raw_downloads>0</raw_downloads><raw_downloads_month>0</raw_downloads_month><raw_downloads_week>0</raw_downloads_week><raw_downloads_day>0</raw_downloads_day><tags>20241210031140</tags></version><version><id>328949539</id><name>sha256:8c6e77bd517361e25fdf8ffeb343388aadc5c0b532dcfd3fd9d1384e2d62ee7b</name><date>2025-04-10</date><newest>false</newest><latest>false</latest><size>138.9 kB</size><downloads>0</downloads><downloads_month>0</downloads_month><downloads_week>0</downloads_week><downloads_day>0</downloads_day><raw_size>138977</raw_size><raw_downloads>0</raw_downloads><raw_downloads_month>0</raw_downloads_month><raw_downloads_week>0</raw_downloads_week><raw_downloads_day>0</raw_downloads_day><tags>20241210044406</tags></version><version><id>328954366</id><name>sha256:efe8410e6eee246092ded5925330259d0634a1660e3451418b4ebf56d989fb94</name><date>2025-04-10</date><newest>false</newest><latest>false</latest><size>73.5 kB</size><downloads>0</downloads><downloads_month>0</downloads_month><downloads_week>0</downloads_week><downloads_day>0</downloads_day><raw_size>73533</raw_size><raw_downloads>0</raw_downloads><raw_downloads_month>0</raw_downloads_month><raw_downloads_week>0</raw_downloads_week><raw_downloads_day>0</raw_downloads_day><tags>20241210031140</tags></version><version><id>329553695</id><name>sha256:aa3fc9ee125fbd15608e512691fff11405b9f81e7935d1f965055710673528c4</name><date>2025-04-10</date><newest>false</newest><latest>false</latest><size>138.9 kB</size><downloads>0</downloads><downloads_month>0</downloads_month><downloads_week>0</downloads_week><downloads_day>0</downloads_day><raw_size>138977</raw_size><raw_downloads>0</raw_downloads><raw_downloads_month>0</raw_downloads_month><raw_downloads_week>0</raw_downloads_week><raw_downloads_day>0</raw_downloads_day><tags>20241210044406</tags></version><version><id>329558508</id><name>sha256:17b54551d78528958be356274ae03fa465580e4137a58178ac503f418824a497</name><date>2025-04-10</date><newest>false</newest><latest>false</latest><size>73.5 kB</size><downloads>0</downloads><downloads_month>0</downloads_month><downloads_week>0</downloads_week><downloads_day>0</downloads_day><raw_size>73533</raw_size><raw_downloads>0</raw_downloads><raw_downloads_month>0</raw_downloads_month><raw_downloads_week>0</raw_downloads_week><raw_downloads_day>0</raw_downloads_day><tags>20241210031140</tags></version><version><id>329869544</id><name>sha256:19a867adee5fa2a589e0acf7618252a17789fd62c76a379e7b4a89580dbbf538</name><date>2025-04-10</date><newest>false</newest><latest>false</latest><size>138.9 kB</size><downloads>0</downloads><downloads_month>0</downloads_month><downloads_week>0</downloads_week><downloads_day>0</downloads_day><raw_size>138977</raw_size><raw_downloads>0</raw_downloads><raw_downloads_month>0</raw_downloads_month><raw_downloads_week>0</raw_downloads_week><raw_downloads_day>0</raw_downloads_day><tags>20241210044406</tags></version><version><id>329873959</id><name>sha256:143d3ce210fa73c117dc8266531fc22ff1e347fae1027c80cbd2238f95aa06ba</name><date>2025-04-10</date><newest>false</newest><latest>false</latest><size>73.5 kB</size><downloads>0</downloads><downloads_month>0</downloads_month><downloads_week>0</downloads_week><downloads_day>0</downloads_day><raw_size>73533</raw_size><raw_downloads>0</raw_downloads><raw_downloads_month>0</raw_downloads_month><raw_downloads_week>0</raw_downloads_week><raw_downloads_day>0</raw_downloads_day><tags>20241210031140</tags></version><version><id>330563665</id><name>sha256:3c851366547ac54935ffa33658c9721df6c2efd83d90513e04375d2c0f0ac33e</name><date>2025-04-10</date><newest>false</newest><latest>false</latest><size>138.9 kB</size><downloads>0</downloads><downloads_month>0</downloads_month><downloads_week>0</downloads_week><downloads_day>0</downloads_day><raw_size>138977</raw_size><raw_downloads>0</raw_downloads><raw_downloads_month>0</raw_downloads_month><raw_downloads_week>0</raw_downloads_week><raw_downloads_day>0</raw_downloads_day><tags>20241210044406</tags><tags>aarch64</tags></version><version><id>330568196</id><name>sha256:e95b880f8d2dd51fa4d43a338080d62acc895ec63e6653bc2d25ccd9edcbc4a4</name><date>2025-04-10</date><newest>true</newest><latest>true</latest><size>73.5 kB</size><downloads>0</downloads><downloads_month>0</downloads_month><downloads_week>0</downloads_week><downloads_day>0</downloads_day><raw_size>73533</raw_size><raw_downloads>0</raw_downloads><raw_downloads_month>0</raw_downloads_month><raw_downloads_week>0</raw_downloads_week><raw_downloads_day>0</raw_downloads_day><tags>20241210031140</tags><tags>x86_64</tags></version></xml>
